bacon/__init__.py
bacon/main.py
bacon/img/bacon.png
baconify-0.0.3.dist-info/LICENSE
baconify-0.0.3.dist-info/METADATA
baconify-0.0.3.dist-info/WHEEL
baconify-0.0.3.dist-info/top_level.txt
baconify-0.0.3.dist-info/RECORD
