Metadata-Version: 2.1
Name: baconify
Version: 0.0.3
Summary: Fill your screen with bacon!
Home-page: https://gitlab.com/jenx/baconify/
Author: Ivana Kellyerova
Author-email: ivana.kellyerova@baconify.amarion.net
License: MIT
Keywords: image,generator,bacon
Platform: UNKNOWN
Classifier: Development Status :: 3 - Alpha
Classifier: Intended Audience :: End Users/Desktop
Classifier: License :: OSI Approved :: MIT License
Classifier: Operating System :: OS Independent
Classifier: Programming Language :: Python
Classifier: Programming Language :: Python :: 3
Classifier: Programming Language :: Python :: 3.5
Classifier: Programming Language :: Python :: 3.6
Classifier: Programming Language :: Python :: 3.7
Classifier: Programming Language :: Python :: 3 :: Only
Classifier: Topic :: Artistic Software
Classifier: Topic :: Multimedia :: Graphics
Requires-Dist: PySide2 (>=5.12.2)
